sphinxcontrib_tikz-0.4.6.dev20180805-py3.6-nspkg.pth
sphinxcontrib/tikz.py
sphinxcontrib_tikz-0.4.6.dev20180805.dist-info/METADATA
sphinxcontrib_tikz-0.4.6.dev20180805.dist-info/PKG-INFO~
sphinxcontrib_tikz-0.4.6.dev20180805.dist-info/RECORD
sphinxcontrib_tikz-0.4.6.dev20180805.dist-info/WHEEL
sphinxcontrib_tikz-0.4.6.dev20180805.dist-info/namespace_packages.txt
sphinxcontrib_tikz-0.4.6.dev20180805.dist-info/top_level.txt
