Metadata-Version: 2.1
Name: sphinxcontrib-tikz
Version: 0.4.6.dev20180805
Summary: TikZ extension for Sphinx
Home-page: https://bitbucket.org/philexander/tikz
Author: Christoph Reller
Author-email: christoph.reller@gmail.com
License: BSD
Download-URL: http://pypi.python.org/pypi/sphinxcontrib-tikz
Platform: any
Classifier: Development Status :: 4 - Beta
Classifier: Environment :: Console
Classifier: Environment :: Web Environment
Classifier: Intended Audience :: Developers
Classifier: License :: OSI Approved :: BSD License
Classifier: Operating System :: OS Independent
Classifier: Programming Language :: Python
Classifier: Programming Language :: Python :: 2
Classifier: Programming Language :: Python :: 2.7
Classifier: Programming Language :: Python :: 3
Classifier: Programming Language :: Python :: 3.4
Classifier: Topic :: Documentation
Classifier: Topic :: Utilities
Requires-Dist: Sphinx
